{
	"success": true,
	"message": "Requests Created!",
	"createdRequests": [
		{
			"title": "Add tags for solutions",
			"description": "Easier to search for solutions based on a specific stack.",
			"category": "Enhancement",
			"status": "Suggestion",
			"user": "620a924cfc6126a3b26be9b6",
			"upvoters": [],
			"numberOfUpvotes": 0,
			"comments": [],
			"numberOfComments": 0,
			"_id": "620e9cd5468e9b386ace033b",
			"createdAt": "2022-02-17T19:07:01.393Z",
			"updatedAt": "2022-02-17T19:07:01.393Z",
			"__v": 0
		},
		{
			"title": "Add a dark theme option",
			"description": "It would help people with light sensitivities and who prefer dark mode.",
			"category": "Feature",
			"status": "Suggestion",
			"user": "620a924cfc6126a3b26be9b6",
			"upvoters": [],
			"numberOfUpvotes": 0,
			"comments": [],
			"numberOfComments": 0,
			"_id": "620e9cd5468e9b386ace033c",
			"createdAt": "2022-02-17T19:07:01.393Z",
			"updatedAt": "2022-02-17T19:07:01.393Z",
			"__v": 0
		},
		{
			"title": "Q&A within the challenge hubs",
			"description": "Challenge-specific Q&A would make for easy reference.",
			"category": "Feature",
			"status": "Suggestion",
			"user": "620a924cfc6126a3b26be9b6",
			"upvoters": [],
			"numberOfUpvotes": 0,
			"comments": [],
			"numberOfComments": 0,
			"_id": "620e9cd5468e9b386ace033d",
			"createdAt": "2022-02-17T19:07:01.393Z",
			"updatedAt": "2022-02-17T19:07:01.393Z",
			"__v": 0
		},
		{
			"title": "Add image/video upload to feedback",
			"description": "Images and screencasts can enhance comments on solutions.",
			"category": "Enhancement",
			"status": "Suggestion",
			"user": "620a924cfc6126a3b26be9b6",
			"upvoters": [],
			"numberOfUpvotes": 0,
			"comments": [],
			"numberOfComments": 0,
			"_id": "620e9cd5468e9b386ace033e",
			"createdAt": "2022-02-17T19:07:01.393Z",
			"updatedAt": "2022-02-17T19:07:01.393Z",
			"__v": 0
		},
		{
			"title": "Ability to follow others",
			"description": "Stay updated on comments and solutions other people post.",
			"category": "Feature",
			"status": "Suggestion",
			"user": "620a924cfc6126a3b26be9b6",
			"upvoters": [],
			"numberOfUpvotes": 0,
			"comments": [],
			"numberOfComments": 0,
			"_id": "620e9cd5468e9b386ace033f",
			"createdAt": "2022-02-17T19:07:01.393Z",
			"updatedAt": "2022-02-17T19:07:01.393Z",
			"__v": 0
		},
		{
			"title": "Preview images not loading",
			"description": "Challenge preview images are missing when you apply a filter.",
			"category": "Bug",
			"status": "Suggestion",
			"user": "620a924cfc6126a3b26be9b6",
			"upvoters": [],
			"numberOfUpvotes": 0,
			"comments": [],
			"numberOfComments": 0,
			"_id": "620e9cd5468e9b386ace0340",
			"createdAt": "2022-02-17T19:07:01.393Z",
			"updatedAt": "2022-02-17T19:07:01.393Z",
			"__v": 0
		},
		{
			"title": "More comprehensive reports",
			"description": "It would be great to see a more detailed breakdown of solutions.",
			"category": "Feature",
			"status": "Planned",
			"user": "620a924cfc6126a3b26be9b6",
			"upvoters": [],
			"numberOfUpvotes": 0,
			"comments": [],
			"numberOfComments": 0,
			"_id": "620e9cd5468e9b386ace0341",
			"createdAt": "2022-02-17T19:07:01.393Z",
			"updatedAt": "2022-02-17T19:07:01.393Z",
			"__v": 0
		},
		{
			"title": "Learning paths",
			"description": "Sequenced projects for different goals to help people improve.",
			"category": "Feature",
			"status": "Planned",
			"user": "620a924cfc6126a3b26be9b6",
			"upvoters": [],
			"numberOfUpvotes": 0,
			"comments": [],
			"numberOfComments": 0,
			"_id": "620e9cd5468e9b386ace0342",
			"createdAt": "2022-02-17T19:07:01.394Z",
			"updatedAt": "2022-02-17T19:07:01.394Z",
			"__v": 0
		},
		{
			"title": "One-click portfolio generation",
			"description": "Add ability to create professional looking portfolio from profile.",
			"category": "Feature",
			"status": "In-Progress",
			"user": "620a924cfc6126a3b26be9b6",
			"upvoters": [],
			"numberOfUpvotes": 0,
			"comments": [],
			"numberOfComments": 0,
			"_id": "620e9cd5468e9b386ace0343",
			"createdAt": "2022-02-17T19:07:01.394Z",
			"updatedAt": "2022-02-17T19:07:01.394Z",
			"__v": 0
		},
		{
			"title": "Bookmark challenges",
			"description": "Be able to bookmark challenges to take later on.",
			"category": "Feature",
			"status": "In-Progress",
			"user": "620a924cfc6126a3b26be9b6",
			"upvoters": [],
			"numberOfUpvotes": 0,
			"comments": [],
			"numberOfComments": 0,
			"_id": "620e9cd5468e9b386ace0344",
			"createdAt": "2022-02-17T19:07:01.394Z",
			"updatedAt": "2022-02-17T19:07:01.394Z",
			"__v": 0
		},
		{
			"title": "Animated solution screenshots",
			"description": "Screenshots of solutions with animations don’t display correctly.",
			"category": "Bug",
			"status": "In-Progress",
			"user": "620a924cfc6126a3b26be9b6",
			"upvoters": [],
			"numberOfUpvotes": 0,
			"comments": [],
			"numberOfComments": 0,
			"_id": "620e9cd5468e9b386ace0345",
			"createdAt": "2022-02-17T19:07:01.394Z",
			"updatedAt": "2022-02-17T19:07:01.394Z",
			"__v": 0
		},
		{
			"title": "Add micro-interactions",
			"description": "Small animations at specific points can add delight.",
			"category": "Enhancement",
			"status": "Live",
			"user": "620a924cfc6126a3b26be9b6",
			"upvoters": [],
			"numberOfUpvotes": 0,
			"comments": [],
			"numberOfComments": 0,
			"_id": "620e9cd5468e9b386ace0346",
			"createdAt": "2022-02-17T19:07:01.394Z",
			"updatedAt": "2022-02-17T19:07:01.394Z",
			"__v": 0
		}
	]
}
